<map_data>
 <name>ms</name>
 <defaultProjection>orthographic</defaultProjection>
 <description><![CDATA[]]></description>
 <columns>
  <column name="REGION_ID" key="true"/>
  <column name="REGION_NAME" key="true"/>
 </columns>
 <bounds left="-91.6435623168945" top="35.004955291748" right="-88.0904312133789" bottom="30.1947383880615"/>
 <regions>
  <region>
   <centroid lat="34.8823089599609" lon="-88.582088470459"/>
   <data>
    <item column="REGION_ID"><value><![CDATA[28003]]></value></item>
    <item column="REGION_NAME"><value><![CDATA[Alcorn]]></value></item>
   </data>
  </region>
  <region>
   <centroid lat="34.7347717285156" lon="-88.2222938537598"/>
   <data>
    <item column="REGION_ID"><value><![CDATA[28141]]></value></item>
    <item column="REGION_NAME"><value><![CDATA[Tishomingo]]></value></item>
   </data>
  </region>
  <region>
   <centroid lat="34.8036136627197" lon="-88.8938827514648"/>
   <data>
    <item column="REGION_ID"><value><![CDATA[28139]]></value></item>
    <item column="REGION_NAME"><value><![CDATA[Tippah]]></value></item>
   </data>
  </region>
  <region>
   <centroid lat="34.7967586517334" lon="-89.1743698120117"/>
   <data>
    <item column="REGION_ID"><value><![CDATA[28009]]></value></item>
    <item column="REGION_NAME"><value><![CDATA[Benton]]></value></item>
   </data>
  </region>
  <region>
   <centroid lat="34.8559379577637" lon="-90.0112686157227"/>
   <data>
    <item column="REGION_ID"><value><![CDATA[28033]]></value></item>
    <item column="REGION_NAME"><value><![CDATA[De Soto]]></value></item>
   </data>
  </region>
  <region>
   <centroid lat="34.7512016296387" lon="-89.4801750183105"/>
   <data>
    <item column="REGION_ID"><value><![CDATA[28093]]></value></item>
    <item column="REGION_NAME"><value><![CDATA[Marshall]]></value></item>
   </data>
  </region>
  <region>
   <centroid lat="34.6558856964111" lon="-90.3928527832031"/>
   <data>
    <item column="REGION_ID"><value><![CDATA[28143]]></value></item>
    <item column="REGION_NAME"><value><![CDATA[Tunica]]></value></item>
   </data>
  </region>
  <region>
   <centroid lat="34.6716785430908" lon="-89.9531135559082"/>
   <data>
    <item column="REGION_ID"><value><![CDATA[28137]]></value></item>
    <item column="REGION_NAME"><value><![CDATA[Tate]]></value></item>
   </data>
  </region>
  <region>
   <centroid lat="34.6148777008057" lon="-88.5218200683594"/>
   <data>
    <item column="REGION_ID"><value><![CDATA[28117]]></value></item>
    <item column="REGION_NAME"><value><![CDATA[Prentiss]]></value></item>
   </data>
  </region>
  <region>
   <centroid lat="34.4890823364258" lon="-88.9821891784668"/>
   <data>
    <item column="REGION_ID"><value><![CDATA[28145]]></value></item>
    <item column="REGION_NAME"><value><![CDATA[Union]]></value></item>
   </data>
  </region>
  <region>
   <centroid lat="34.3659000396729" lon="-89.4780235290527"/>
   <data>
    <item column="REGION_ID"><value><![CDATA[28071]]></value></item>
    <item column="REGION_NAME"><value><![CDATA[Lafayette]]></value></item>
   </data>
  </region>
  <region>
   <centroid lat="34.3633975982666" lon="-89.957592010498"/>
   <data>
    <item column="REGION_ID"><value><![CDATA[28107]]></value></item>
    <item column="REGION_NAME"><value><![CDATA[Panola]]></value></item>
   </data>
  </region>
  <region>
   <centroid lat="34.2592658996582" lon="-90.6745491027832"/>
   <data>
    <item column="REGION_ID"><value><![CDATA[28027]]></value></item>
    <item column="REGION_NAME"><value><![CDATA[Coahoma]]></value></item>
   </data>
  </region>
  <region>
   <centroid lat="34.300708770752" lon="-88.6757049560547"/>
   <data>
    <item column="REGION_ID"><value><![CDATA[28081]]></value></item>
    <item column="REGION_NAME"><value><![CDATA[Lee]]></value></item>
   </data>
  </region>
  <region>
   <centroid lat="34.2988471984863" lon="-90.2905464172363"/>
   <data>
    <item column="REGION_ID"><value><![CDATA[28119]]></value></item>
    <item column="REGION_NAME"><value><![CDATA[Quitman]]></value></item>
   </data>
  </region>
  <region>
   <centroid lat="34.2798194885254" lon="-88.3456726074219"/>
   <data>
    <item column="REGION_ID"><value><![CDATA[28057]]></value></item>
    <item column="REGION_NAME"><value><![CDATA[Itawamba]]></value></item>
   </data>
  </region>
  <region>
   <centroid lat="34.2313652038574" lon="-89.0299644470215"/>
   <data>
    <item column="REGION_ID"><value><![CDATA[28115]]></value></item>
    <item column="REGION_NAME"><value><![CDATA[Pontotoc]]></value></item>
   </data>
  </region>
  <region>
   <centroid lat="34.0328502655029" lon="-89.7179946899414"/>
   <data>
    <item column="REGION_ID"><value><![CDATA[28161]]></value></item>
    <item column="REGION_NAME"><value><![CDATA[Yalobusha]]></value></item>
   </data>
  </region>
  <region>
   <centroid lat="33.9322166442871" lon="-90.1889533996582"/>
   <data>
    <item column="REGION_ID"><value><![CDATA[28135]]></value></item>
    <item column="REGION_NAME"><value><![CDATA[Tallahatchie]]></value></item>
   </data>
  </region>
  <region>
   <centroid lat="33.9454135894775" lon="-89.3190002441406"/>
   <data>
    <item column="REGION_ID"><value><![CDATA[28013]]></value></item>
    <item column="REGION_NAME"><value><![CDATA[Calhoun]]></value></item>
   </data>
  </region>
  <region>
   <centroid lat="33.8318862915039" lon="-90.9424133300781"/>
   <data>
    <item column="REGION_ID"><value><![CDATA[28011]]></value></item>
    <item column="REGION_NAME"><value><![CDATA[Bolivar]]></value></item>
   </data>
  </region>
  <region>
   <centroid lat="33.8736629486084" lon="-88.4570045471191"/>
   <data>
    <item column="REGION_ID"><value><![CDATA[28095]]></value></item>
    <item column="REGION_NAME"><value><![CDATA[Monroe]]></value></item>
   </data>
  </region>
  <region>
   <centroid lat="33.9121570587158" lon="-88.9460830688477"/>
   <data>
    <item column="REGION_ID"><value><![CDATA[28017]]></value></item>
    <item column="REGION_NAME"><value><![CDATA[Chickasaw]]></value></item>
   </data>
  </region>
  <region>
   <centroid lat="33.6332817077637" lon="-90.6068267822266"/>
   <data>
    <item column="REGION_ID"><value><![CDATA[28133]]></value></item>
    <item column="REGION_NAME"><value><![CDATA[Sunflower]]></value></item>
   </data>
  </region>
  <region>
   <centroid lat="33.7872695922852" lon="-89.8180732727051"/>
   <data>
    <item column="REGION_ID"><value><![CDATA[28043]]></value></item>
    <item column="REGION_NAME"><value><![CDATA[Grenada]]></value></item>
   </data>
  </region>
  <region>
   <centroid lat="33.5300426483154" lon="-90.2719230651855"/>
   <data>
    <item column="REGION_ID"><value><![CDATA[28083]]></value></item>
    <item column="REGION_NAME"><value><![CDATA[Leflore]]></value></item>
   </data>
  </region>
  <region>
   <centroid lat="33.6614532470703" lon="-88.7479858398438"/>
   <data>
    <item column="REGION_ID"><value><![CDATA[28025]]></value></item>
    <item column="REGION_NAME"><value><![CDATA[Clay]]></value></item>
   </data>
  </region>
  <region>
   <centroid lat="33.5178565979004" lon="-88.4584693908691"/>
   <data>
    <item column="REGION_ID"><value><![CDATA[28087]]></value></item>
    <item column="REGION_NAME"><value><![CDATA[Lowndes]]></value></item>
   </data>
  </region>
  <region>
   <centroid lat="33.603385925293" lon="-89.2564811706543"/>
   <data>
    <item column="REGION_ID"><value><![CDATA[28155]]></value></item>
    <item column="REGION_NAME"><value><![CDATA[Webster]]></value></item>
   </data>
  </region>
  <region>
   <centroid lat="33.4525203704834" lon="-89.9063415527344"/>
   <data>
    <item column="REGION_ID"><value><![CDATA[28015]]></value></item>
    <item column="REGION_NAME"><value><![CDATA[Carroll]]></value></item>
   </data>
  </region>
  <region>
   <centroid lat="33.4858665466309" lon="-89.5832061767578"/>
   <data>
    <item column="REGION_ID"><value><![CDATA[28097]]></value></item>
    <item column="REGION_NAME"><value><![CDATA[Montgomery]]></value></item>
   </data>
  </region>
  <region>
   <centroid lat="33.4321880340576" lon="-88.8734970092773"/>
   <data>
    <item column="REGION_ID"><value><![CDATA[28105]]></value></item>
    <item column="REGION_NAME"><value><![CDATA[Oktibbeha]]></value></item>
   </data>
  </region>
  <region>
   <centroid lat="33.2785816192627" lon="-90.9540786743164"/>
   <data>
    <item column="REGION_ID"><value><![CDATA[28151]]></value></item>
    <item column="REGION_NAME"><value><![CDATA[Washington]]></value></item>
   </data>
  </region>
  <region>
   <centroid lat="33.3272743225098" lon="-89.2660217285156"/>
   <data>
    <item column="REGION_ID"><value><![CDATA[28019]]></value></item>
    <item column="REGION_NAME"><value><![CDATA[Choctaw]]></value></item>
   </data>
  </region>
  <region>
   <centroid lat="33.1342124938965" lon="-90.0867538452148"/>
   <data>
    <item column="REGION_ID"><value><![CDATA[28051]]></value></item>
    <item column="REGION_NAME"><value><![CDATA[Holmes]]></value></item>
   </data>
  </region>
  <region>
   <centroid lat="33.1290149688721" lon="-90.5269203186035"/>
   <data>
    <item column="REGION_ID"><value><![CDATA[28053]]></value></item>
    <item column="REGION_NAME"><value><![CDATA[Humphreys]]></value></item>
   </data>
  </region>
  <region>
   <centroid lat="33.0898551940918" lon="-89.6390838623047"/>
   <data>
    <item column="REGION_ID"><value><![CDATA[28007]]></value></item>
    <item column="REGION_NAME"><value><![CDATA[Attala]]></value></item>
   </data>
  </region>
  <region>
   <centroid lat="33.107852935791" lon="-88.5573425292969"/>
   <data>
    <item column="REGION_ID"><value><![CDATA[28103]]></value></item>
    <item column="REGION_NAME"><value><![CDATA[Noxubee]]></value></item>
   </data>
  </region>
  <region>
   <centroid lat="33.1052742004395" lon="-89.0616874694824"/>
   <data>
    <item column="REGION_ID"><value><![CDATA[28159]]></value></item>
    <item column="REGION_NAME"><value><![CDATA[Winston]]></value></item>
   </data>
  </region>
  <region>
   <centroid lat="32.8884334564209" lon="-90.806713104248"/>
   <data>
    <item column="REGION_ID"><value><![CDATA[28125]]></value></item>
    <item column="REGION_NAME"><value><![CDATA[Sharkey]]></value></item>
   </data>
  </region>
  <region>
   <centroid lat="32.7694473266602" lon="-90.3576889038086"/>
   <data>
    <item column="REGION_ID"><value><![CDATA[28163]]></value></item>
    <item column="REGION_NAME"><value><![CDATA[Yazoo]]></value></item>
   </data>
  </region>
  <region>
   <centroid lat="32.7298011779785" lon="-90.9486694335938"/>
   <data>
    <item column="REGION_ID"><value><![CDATA[28055]]></value></item>
    <item column="REGION_NAME"><value><![CDATA[Issaquena]]></value></item>
   </data>
  </region>
  <region>
   <centroid lat="32.757474899292" lon="-89.1145553588867"/>
   <data>
    <item column="REGION_ID"><value><![CDATA[28099]]></value></item>
    <item column="REGION_NAME"><value><![CDATA[Neshoba]]></value></item>
   </data>
  </region>
  <region>
   <centroid lat="32.7556190490723" lon="-89.5226783752441"/>
   <data>
    <item column="REGION_ID"><value><![CDATA[28079]]></value></item>
    <item column="REGION_NAME"><value><![CDATA[Leake]]></value></item>
   </data>
  </region>
  <region>
   <centroid lat="32.7553615570068" lon="-88.6299133300781"/>
   <data>
    <item column="REGION_ID"><value><![CDATA[28069]]></value></item>
    <item column="REGION_NAME"><value><![CDATA[Kemper]]></value></item>
   </data>
  </region>
  <region>
   <centroid lat="32.6461124420166" lon="-90.0847816467285"/>
   <data>
    <item column="REGION_ID"><value><![CDATA[28089]]></value></item>
    <item column="REGION_NAME"><value><![CDATA[Madison]]></value></item>
   </data>
  </region>
  <region>
   <centroid lat="32.4330787658691" lon="-89.5519828796387"/>
   <data>
    <item column="REGION_ID"><value><![CDATA[28123]]></value></item>
    <item column="REGION_NAME"><value><![CDATA[Scott]]></value></item>
   </data>
  </region>
  <region>
   <centroid lat="32.34010887146" lon="-90.8595962524414"/>
   <data>
    <item column="REGION_ID"><value><![CDATA[28149]]></value></item>
    <item column="REGION_NAME"><value><![CDATA[Warren]]></value></item>
   </data>
  </region>
  <region>
   <centroid lat="32.3261375427246" lon="-89.9853477478027"/>
   <data>
    <item column="REGION_ID"><value><![CDATA[28121]]></value></item>
    <item column="REGION_NAME"><value><![CDATA[Rankin]]></value></item>
   </data>
  </region>
  <region>
   <centroid lat="32.4039726257324" lon="-88.6551704406738"/>
   <data>
    <item column="REGION_ID"><value><![CDATA[28075]]></value></item>
    <item column="REGION_NAME"><value><![CDATA[Lauderdale]]></value></item>
   </data>
  </region>
  <region>
   <centroid lat="32.4051532745361" lon="-89.1170654296875"/>
   <data>
    <item column="REGION_ID"><value><![CDATA[28101]]></value></item>
    <item column="REGION_NAME"><value><![CDATA[Newton]]></value></item>
   </data>
  </region>
  <region>
   <centroid lat="32.3118362426758" lon="-90.3960800170898"/>
   <data>
    <item column="REGION_ID"><value><![CDATA[28049]]></value></item>
    <item column="REGION_NAME"><value><![CDATA[Hinds]]></value></item>
   </data>
  </region>
  <region>
   <centroid lat="32.0190896987915" lon="-89.1116600036621"/>
   <data>
    <item column="REGION_ID"><value><![CDATA[28061]]></value></item>
    <item column="REGION_NAME"><value><![CDATA[Jasper]]></value></item>
   </data>
  </region>
  <region>
   <centroid lat="32.0299882888794" lon="-88.677116394043"/>
   <data>
    <item column="REGION_ID"><value><![CDATA[28023]]></value></item>
    <item column="REGION_NAME"><value><![CDATA[Clarke]]></value></item>
   </data>
  </region>
  <region>
   <centroid lat="32.0074787139893" lon="-89.5246429443359"/>
   <data>
    <item column="REGION_ID"><value><![CDATA[28129]]></value></item>
    <item column="REGION_NAME"><value><![CDATA[Smith]]></value></item>
   </data>
  </region>
  <region>
   <centroid lat="32.0099925994873" lon="-90.9784164428711"/>
   <data>
    <item column="REGION_ID"><value><![CDATA[28021]]></value></item>
    <item column="REGION_NAME"><value><![CDATA[Claiborne]]></value></item>
   </data>
  </region>
  <region>
   <centroid lat="31.9074640274048" lon="-89.9441833496094"/>
   <data>
    <item column="REGION_ID"><value><![CDATA[28127]]></value></item>
    <item column="REGION_NAME"><value><![CDATA[Simpson]]></value></item>
   </data>
  </region>
  <region>
   <centroid lat="31.8720235824585" lon="-90.4215507507324"/>
   <data>
    <item column="REGION_ID"><value><![CDATA[28029]]></value></item>
    <item column="REGION_NAME"><value><![CDATA[Copiah]]></value></item>
   </data>
  </region>
  <region>
   <centroid lat="31.6620864868164" lon="-88.6902542114258"/>
   <data>
    <item column="REGION_ID"><value><![CDATA[28153]]></value></item>
    <item column="REGION_NAME"><value><![CDATA[Wayne]]></value></item>
   </data>
  </region>
  <region>
   <centroid lat="31.7468852996826" lon="-91.0510864257813"/>
   <data>
    <item column="REGION_ID"><value><![CDATA[28063]]></value></item>
    <item column="REGION_NAME"><value><![CDATA[Jefferson]]></value></item>
   </data>
  </region>
  <region>
   <centroid lat="31.631462097168" lon="-89.1642570495605"/>
   <data>
    <item column="REGION_ID"><value><![CDATA[28067]]></value></item>
    <item column="REGION_NAME"><value><![CDATA[Jones]]></value></item>
   </data>
  </region>
  <region>
   <centroid lat="31.6180467605591" lon="-89.5737686157227"/>
   <data>
    <item column="REGION_ID"><value><![CDATA[28031]]></value></item>
    <item column="REGION_NAME"><value><![CDATA[Covington]]></value></item>
   </data>
  </region>
  <region>
   <centroid lat="31.585319519043" lon="-89.7778549194336"/>
   <data>
    <item column="REGION_ID"><value><![CDATA[28065]]></value></item>
    <item column="REGION_NAME"><value><![CDATA[Jefferson Davis]]></value></item>
   </data>
  </region>
  <region>
   <centroid lat="31.5502271652222" lon="-90.101001739502"/>
   <data>
    <item column="REGION_ID"><value><![CDATA[28077]]></value></item>
    <item column="REGION_NAME"><value><![CDATA[Lawrence]]></value></item>
   </data>
  </region>
  <region>
   <centroid lat="31.4860668182373" lon="-91.3989105224609"/>
   <data>
    <item column="REGION_ID"><value><![CDATA[28001]]></value></item>
    <item column="REGION_NAME"><value><![CDATA[Adams]]></value></item>
   </data>
  </region>
  <region>
   <centroid lat="31.5398693084717" lon="-90.4904327392578"/>
   <data>
    <item column="REGION_ID"><value><![CDATA[28085]]></value></item>
    <item column="REGION_NAME"><value><![CDATA[Lincoln]]></value></item>
   </data>
  </region>
  <region>
   <centroid lat="31.4729347229004" lon="-90.8943786621094"/>
   <data>
    <item column="REGION_ID"><value><![CDATA[28037]]></value></item>
    <item column="REGION_NAME"><value><![CDATA[Franklin]]></value></item>
   </data>
  </region>
  <region>
   <centroid lat="31.2232322692871" lon="-89.8454055786133"/>
   <data>
    <item column="REGION_ID"><value><![CDATA[28091]]></value></item>
    <item column="REGION_NAME"><value><![CDATA[Marion]]></value></item>
   </data>
  </region>
  <region>
   <centroid lat="31.2136383056641" lon="-89.4991912841797"/>
   <data>
    <item column="REGION_ID"><value><![CDATA[28073]]></value></item>
    <item column="REGION_NAME"><value><![CDATA[Lamar]]></value></item>
   </data>
  </region>
  <region>
   <centroid lat="31.1770429611206" lon="-89.2893333435059"/>
   <data>
    <item column="REGION_ID"><value><![CDATA[28035]]></value></item>
    <item column="REGION_NAME"><value><![CDATA[Forrest]]></value></item>
   </data>
  </region>
  <region>
   <centroid lat="31.1754713058472" lon="-88.9819259643555"/>
   <data>
    <item column="REGION_ID"><value><![CDATA[28111]]></value></item>
    <item column="REGION_NAME"><value><![CDATA[Perry]]></value></item>
   </data>
  </region>
  <region>
   <centroid lat="31.2182922363281" lon="-88.6319236755371"/>
   <data>
    <item column="REGION_ID"><value><![CDATA[28041]]></value></item>
    <item column="REGION_NAME"><value><![CDATA[Greene]]></value></item>
   </data>
  </region>
  <region>
   <centroid lat="31.1885566711426" lon="-91.3445434570313"/>
   <data>
    <item column="REGION_ID"><value><![CDATA[28157]]></value></item>
    <item column="REGION_NAME"><value><![CDATA[Wilkinson]]></value></item>
   </data>
  </region>
  <region>
   <centroid lat="31.1797828674316" lon="-90.8235244750977"/>
   <data>
    <item column="REGION_ID"><value><![CDATA[28005]]></value></item>
    <item column="REGION_NAME"><value><![CDATA[Amite]]></value></item>
   </data>
  </region>
  <region>
   <centroid lat="31.1807241439819" lon="-90.400577545166"/>
   <data>
    <item column="REGION_ID"><value><![CDATA[28113]]></value></item>
    <item column="REGION_NAME"><value><![CDATA[Pike]]></value></item>
   </data>
  </region>
  <region>
   <centroid lat="31.1831493377686" lon="-90.0463829040527"/>
   <data>
    <item column="REGION_ID"><value><![CDATA[28147]]></value></item>
    <item column="REGION_NAME"><value><![CDATA[Walthall]]></value></item>
   </data>
  </region>
  <region>
   <centroid lat="30.743688583374" lon="-89.5879440307617"/>
   <data>
    <item column="REGION_ID"><value><![CDATA[28109]]></value></item>
    <item column="REGION_NAME"><value><![CDATA[Pearl River]]></value></item>
   </data>
  </region>
  <region>
   <centroid lat="30.8687925338745" lon="-88.6444282531738"/>
   <data>
    <item column="REGION_ID"><value><![CDATA[28039]]></value></item>
    <item column="REGION_NAME"><value><![CDATA[George]]></value></item>
   </data>
  </region>
  <region>
   <centroid lat="30.7834548950195" lon="-89.1022872924805"/>
   <data>
    <item column="REGION_ID"><value><![CDATA[28131]]></value></item>
    <item column="REGION_NAME"><value><![CDATA[Stone]]></value></item>
   </data>
  </region>
  <region>
   <centroid lat="30.5325984954834" lon="-88.6364860534668"/>
   <data>
    <item column="REGION_ID"><value><![CDATA[28059]]></value></item>
    <item column="REGION_NAME"><value><![CDATA[Jackson]]></value></item>
   </data>
  </region>
  <region>
   <centroid lat="30.4989175796509" lon="-89.1036834716797"/>
   <data>
    <item column="REGION_ID"><value><![CDATA[28047]]></value></item>
    <item column="REGION_NAME"><value><![CDATA[Harrison]]></value></item>
   </data>
  </region>
  <region>
   <centroid lat="30.4244966506958" lon="-89.5009422302246"/>
   <data>
    <item column="REGION_ID"><value><![CDATA[28045]]></value></item>
    <item column="REGION_NAME"><value><![CDATA[Hancock]]></value></item>
   </data>
  </region>
 </regions>
</map_data>