<map_data>
 <name>tn</name>
 <defaultProjection>orthographic</defaultProjection>
 <description><![CDATA[]]></description>
 <columns>
  <column name="REGION_ID" key="true"/>
  <column name="REGION_NAME" key="true"/>
 </columns>
 <bounds left="-90.3053512573242" top="36.679630279541" right="-81.6524353027344" bottom="34.9886817932129"/>
 <regions>
  <region>
   <centroid lat="36.5052700042725" lon="-87.8305015563965"/>
   <data>
    <item column="REGION_ID"><value><![CDATA[47161]]></value></item>
    <item column="REGION_NAME"><value><![CDATA[Stewart]]></value></item>
   </data>
  </region>
  <region>
   <centroid lat="36.5009689331055" lon="-86.8245391845703"/>
   <data>
    <item column="REGION_ID"><value><![CDATA[47147]]></value></item>
    <item column="REGION_NAME"><value><![CDATA[Robertson]]></value></item>
   </data>
  </region>
  <region>
   <centroid lat="36.4491806030273" lon="-86.4751739501953"/>
   <data>
    <item column="REGION_ID"><value><![CDATA[47165]]></value></item>
    <item column="REGION_NAME"><value><![CDATA[Sumner]]></value></item>
   </data>
  </region>
  <region>
   <centroid lat="36.4864559173584" lon="-87.3766708374023"/>
   <data>
    <item column="REGION_ID"><value><![CDATA[47125]]></value></item>
    <item column="REGION_NAME"><value><![CDATA[Montgomery]]></value></item>
   </data>
  </region>
  <region>
   <centroid lat="36.5297508239746" lon="-86.0039443969727"/>
   <data>
    <item column="REGION_ID"><value><![CDATA[47111]]></value></item>
    <item column="REGION_NAME"><value><![CDATA[Macon]]></value></item>
   </data>
  </region>
  <region>
   <centroid lat="36.5190391540527" lon="-85.5391616821289"/>
   <data>
    <item column="REGION_ID"><value><![CDATA[47027]]></value></item>
    <item column="REGION_NAME"><value><![CDATA[Clay]]></value></item>
   </data>
  </region>
  <region>
   <centroid lat="36.5188808441162" lon="-85.0073852539063"/>
   <data>
    <item column="REGION_ID"><value><![CDATA[47137]]></value></item>
    <item column="REGION_NAME"><value><![CDATA[Pickett]]></value></item>
   </data>
  </region>
  <region>
   <centroid lat="36.5036010742188" lon="-82.2661819458008"/>
   <data>
    <item column="REGION_ID"><value><![CDATA[47163]]></value></item>
    <item column="REGION_NAME"><value><![CDATA[Sullivan]]></value></item>
   </data>
  </region>
  <region>
   <centroid lat="36.4374008178711" lon="-81.8501472473145"/>
   <data>
    <item column="REGION_ID"><value><![CDATA[47091]]></value></item>
    <item column="REGION_NAME"><value><![CDATA[Johnson]]></value></item>
   </data>
  </region>
  <region>
   <centroid lat="36.3869037628174" lon="-84.513973236084"/>
   <data>
    <item column="REGION_ID"><value><![CDATA[47151]]></value></item>
    <item column="REGION_NAME"><value><![CDATA[Scott]]></value></item>
   </data>
  </region>
  <region>
   <centroid lat="36.4938774108887" lon="-83.1571197509766"/>
   <data>
    <item column="REGION_ID"><value><![CDATA[47067]]></value></item>
    <item column="REGION_NAME"><value><![CDATA[Hancock]]></value></item>
   </data>
  </region>
  <region>
   <centroid lat="36.4635257720947" lon="-83.6857490539551"/>
   <data>
    <item column="REGION_ID"><value><![CDATA[47025]]></value></item>
    <item column="REGION_NAME"><value><![CDATA[Claiborne]]></value></item>
   </data>
  </region>
  <region>
   <centroid lat="36.3862133026123" lon="-84.1387977600098"/>
   <data>
    <item column="REGION_ID"><value><![CDATA[47013]]></value></item>
    <item column="REGION_NAME"><value><![CDATA[Campbell]]></value></item>
   </data>
  </region>
  <region>
   <centroid lat="36.4151458740234" lon="-82.9433364868164"/>
   <data>
    <item column="REGION_ID"><value><![CDATA[47073]]></value></item>
    <item column="REGION_NAME"><value><![CDATA[Hawkins]]></value></item>
   </data>
  </region>
  <region>
   <centroid lat="36.3624210357666" lon="-84.8853797912598"/>
   <data>
    <item column="REGION_ID"><value><![CDATA[47049]]></value></item>
    <item column="REGION_NAME"><value><![CDATA[Fentress]]></value></item>
   </data>
  </region>
  <region>
   <centroid lat="36.3469257354736" lon="-85.2838897705078"/>
   <data>
    <item column="REGION_ID"><value><![CDATA[47133]]></value></item>
    <item column="REGION_NAME"><value><![CDATA[Overton]]></value></item>
   </data>
  </region>
  <region>
   <centroid lat="36.36985206604" lon="-85.66748046875"/>
   <data>
    <item column="REGION_ID"><value><![CDATA[47087]]></value></item>
    <item column="REGION_NAME"><value><![CDATA[Jackson]]></value></item>
   </data>
  </region>
  <region>
   <centroid lat="36.2997550964355" lon="-82.137321472168"/>
   <data>
    <item column="REGION_ID"><value><![CDATA[47019]]></value></item>
    <item column="REGION_NAME"><value><![CDATA[Carter]]></value></item>
   </data>
  </region>
  <region>
   <centroid lat="36.3431797027588" lon="-89.518856048584"/>
   <data>
    <item column="REGION_ID"><value><![CDATA[47095]]></value></item>
    <item column="REGION_NAME"><value><![CDATA[Lake]]></value></item>
   </data>
  </region>
  <region>
   <centroid lat="36.3520908355713" lon="-89.1415786743164"/>
   <data>
    <item column="REGION_ID"><value><![CDATA[47131]]></value></item>
    <item column="REGION_NAME"><value><![CDATA[Obion]]></value></item>
   </data>
  </region>
  <region>
   <centroid lat="36.2837543487549" lon="-88.734561920166"/>
   <data>
    <item column="REGION_ID"><value><![CDATA[47183]]></value></item>
    <item column="REGION_NAME"><value><![CDATA[Weakley]]></value></item>
   </data>
  </region>
  <region>
   <centroid lat="36.3154697418213" lon="-88.2594909667969"/>
   <data>
    <item column="REGION_ID"><value><![CDATA[47079]]></value></item>
    <item column="REGION_NAME"><value><![CDATA[Henry]]></value></item>
   </data>
  </region>
  <region>
   <centroid lat="36.396053314209" lon="-86.1264419555664"/>
   <data>
    <item column="REGION_ID"><value><![CDATA[47169]]></value></item>
    <item column="REGION_NAME"><value><![CDATA[Trousdale]]></value></item>
   </data>
  </region>
  <region>
   <centroid lat="36.2550239562988" lon="-87.0924873352051"/>
   <data>
    <item column="REGION_ID"><value><![CDATA[47021]]></value></item>
    <item column="REGION_NAME"><value><![CDATA[Cheatham]]></value></item>
   </data>
  </region>
  <region>
   <centroid lat="36.2709846496582" lon="-82.4942665100098"/>
   <data>
    <item column="REGION_ID"><value><![CDATA[47179]]></value></item>
    <item column="REGION_NAME"><value><![CDATA[Washington]]></value></item>
   </data>
  </region>
  <region>
   <centroid lat="36.3006324768066" lon="-83.8448944091797"/>
   <data>
    <item column="REGION_ID"><value><![CDATA[47173]]></value></item>
    <item column="REGION_NAME"><value><![CDATA[Union]]></value></item>
   </data>
  </region>
  <region>
   <centroid lat="36.2597389221191" lon="-85.9552154541016"/>
   <data>
    <item column="REGION_ID"><value><![CDATA[47159]]></value></item>
    <item column="REGION_NAME"><value><![CDATA[Smith]]></value></item>
   </data>
  </region>
  <region>
   <centroid lat="36.2520961761475" lon="-83.4957122802734"/>
   <data>
    <item column="REGION_ID"><value><![CDATA[47057]]></value></item>
    <item column="REGION_NAME"><value><![CDATA[Grainger]]></value></item>
   </data>
  </region>
  <region>
   <centroid lat="36.1685905456543" lon="-82.8707542419434"/>
   <data>
    <item column="REGION_ID"><value><![CDATA[47059]]></value></item>
    <item column="REGION_NAME"><value><![CDATA[Greene]]></value></item>
   </data>
  </region>
  <region>
   <centroid lat="36.1877117156982" lon="-86.7761116027832"/>
   <data>
    <item column="REGION_ID"><value><![CDATA[47037]]></value></item>
    <item column="REGION_NAME"><value><![CDATA[Davidson]]></value></item>
   </data>
  </region>
  <region>
   <centroid lat="36.2783336639404" lon="-87.7485694885254"/>
   <data>
    <item column="REGION_ID"><value><![CDATA[47083]]></value></item>
    <item column="REGION_NAME"><value><![CDATA[Houston]]></value></item>
   </data>
  </region>
  <region>
   <centroid lat="36.1422958374023" lon="-84.6231117248535"/>
   <data>
    <item column="REGION_ID"><value><![CDATA[47129]]></value></item>
    <item column="REGION_NAME"><value><![CDATA[Morgan]]></value></item>
   </data>
  </region>
  <region>
   <centroid lat="36.0883846282959" lon="-88.0650749206543"/>
   <data>
    <item column="REGION_ID"><value><![CDATA[47005]]></value></item>
    <item column="REGION_NAME"><value><![CDATA[Benton]]></value></item>
   </data>
  </region>
  <region>
   <centroid lat="36.1532936096191" lon="-86.2940788269043"/>
   <data>
    <item column="REGION_ID"><value><![CDATA[47189]]></value></item>
    <item column="REGION_NAME"><value><![CDATA[Wilson]]></value></item>
   </data>
  </region>
  <region>
   <centroid lat="36.23219871521" lon="-83.2764358520508"/>
   <data>
    <item column="REGION_ID"><value><![CDATA[47063]]></value></item>
    <item column="REGION_NAME"><value><![CDATA[Hamblen]]></value></item>
   </data>
  </region>
  <region>
   <centroid lat="36.153865814209" lon="-87.3466033935547"/>
   <data>
    <item column="REGION_ID"><value><![CDATA[47043]]></value></item>
    <item column="REGION_NAME"><value><![CDATA[Dickson]]></value></item>
   </data>
  </region>
  <region>
   <centroid lat="36.1472702026367" lon="-85.4512138366699"/>
   <data>
    <item column="REGION_ID"><value><![CDATA[47141]]></value></item>
    <item column="REGION_NAME"><value><![CDATA[Putnam]]></value></item>
   </data>
  </region>
  <region>
   <centroid lat="36.0995616912842" lon="-84.1951713562012"/>
   <data>
    <item column="REGION_ID"><value><![CDATA[47001]]></value></item>
    <item column="REGION_NAME"><value><![CDATA[Anderson]]></value></item>
   </data>
  </region>
  <region>
   <centroid lat="36.1074237823486" lon="-82.4067687988281"/>
   <data>
    <item column="REGION_ID"><value><![CDATA[47171]]></value></item>
    <item column="REGION_NAME"><value><![CDATA[Unicoi]]></value></item>
   </data>
  </region>
  <region>
   <centroid lat="36.0312252044678" lon="-87.7681732177734"/>
   <data>
    <item column="REGION_ID"><value><![CDATA[47085]]></value></item>
    <item column="REGION_NAME"><value><![CDATA[Humphreys]]></value></item>
   </data>
  </region>
  <region>
   <centroid lat="36.011510848999" lon="-88.9463500976563"/>
   <data>
    <item column="REGION_ID"><value><![CDATA[47053]]></value></item>
    <item column="REGION_NAME"><value><![CDATA[Gibson]]></value></item>
   </data>
  </region>
  <region>
   <centroid lat="36.0472011566162" lon="-89.4389801025391"/>
   <data>
    <item column="REGION_ID"><value><![CDATA[47045]]></value></item>
    <item column="REGION_NAME"><value><![CDATA[Dyer]]></value></item>
   </data>
  </region>
  <region>
   <centroid lat="35.9935741424561" lon="-83.9568786621094"/>
   <data>
    <item column="REGION_ID"><value><![CDATA[47093]]></value></item>
    <item column="REGION_NAME"><value><![CDATA[Knox]]></value></item>
   </data>
  </region>
  <region>
   <centroid lat="36.044002532959" lon="-83.4655418395996"/>
   <data>
    <item column="REGION_ID"><value><![CDATA[47089]]></value></item>
    <item column="REGION_NAME"><value><![CDATA[Jefferson]]></value></item>
   </data>
  </region>
  <region>
   <centroid lat="35.9427909851074" lon="-83.1030311584473"/>
   <data>
    <item column="REGION_ID"><value><![CDATA[47029]]></value></item>
    <item column="REGION_NAME"><value><![CDATA[Cocke]]></value></item>
   </data>
  </region>
  <region>
   <centroid lat="35.9628200531006" lon="-84.9751815795898"/>
   <data>
    <item column="REGION_ID"><value><![CDATA[47035]]></value></item>
    <item column="REGION_NAME"><value><![CDATA[Cumberland]]></value></item>
   </data>
  </region>
  <region>
   <centroid lat="35.9732761383057" lon="-88.4399261474609"/>
   <data>
    <item column="REGION_ID"><value><![CDATA[47017]]></value></item>
    <item column="REGION_NAME"><value><![CDATA[Carroll]]></value></item>
   </data>
  </region>
  <region>
   <centroid lat="35.9834938049316" lon="-85.8433837890625"/>
   <data>
    <item column="REGION_ID"><value><![CDATA[47041]]></value></item>
    <item column="REGION_NAME"><value><![CDATA[De Kalb]]></value></item>
   </data>
  </region>
  <region>
   <centroid lat="35.8594303131104" lon="-86.413330078125"/>
   <data>
    <item column="REGION_ID"><value><![CDATA[47149]]></value></item>
    <item column="REGION_NAME"><value><![CDATA[Rutherford]]></value></item>
   </data>
  </region>
  <region>
   <centroid lat="35.943115234375" lon="-85.4393463134766"/>
   <data>
    <item column="REGION_ID"><value><![CDATA[47185]]></value></item>
    <item column="REGION_NAME"><value><![CDATA[White]]></value></item>
   </data>
  </region>
  <region>
   <centroid lat="35.8531951904297" lon="-84.5241203308105"/>
   <data>
    <item column="REGION_ID"><value><![CDATA[47145]]></value></item>
    <item column="REGION_NAME"><value><![CDATA[Roane]]></value></item>
   </data>
  </region>
  <region>
   <centroid lat="35.8799266815186" lon="-86.910041809082"/>
   <data>
    <item column="REGION_ID"><value><![CDATA[47187]]></value></item>
    <item column="REGION_NAME"><value><![CDATA[Williamson]]></value></item>
   </data>
  </region>
  <region>
   <centroid lat="35.8003215789795" lon="-83.5193061828613"/>
   <data>
    <item column="REGION_ID"><value><![CDATA[47155]]></value></item>
    <item column="REGION_NAME"><value><![CDATA[Sevier]]></value></item>
   </data>
  </region>
  <region>
   <centroid lat="35.808277130127" lon="-87.4711303710938"/>
   <data>
    <item column="REGION_ID"><value><![CDATA[47081]]></value></item>
    <item column="REGION_NAME"><value><![CDATA[Hickman]]></value></item>
   </data>
  </region>
  <region>
   <centroid lat="35.8349266052246" lon="-89.1319770812988"/>
   <data>
    <item column="REGION_ID"><value><![CDATA[47033]]></value></item>
    <item column="REGION_NAME"><value><![CDATA[Crockett]]></value></item>
   </data>
  </region>
  <region>
   <centroid lat="35.8136615753174" lon="-86.0452003479004"/>
   <data>
    <item column="REGION_ID"><value><![CDATA[47015]]></value></item>
    <item column="REGION_NAME"><value><![CDATA[Cannon]]></value></item>
   </data>
  </region>
  <region>
   <centroid lat="35.7494812011719" lon="-89.6498222351074"/>
   <data>
    <item column="REGION_ID"><value><![CDATA[47097]]></value></item>
    <item column="REGION_NAME"><value><![CDATA[Lauderdale]]></value></item>
   </data>
  </region>
  <region>
   <centroid lat="35.7608127593994" lon="-84.3527336120605"/>
   <data>
    <item column="REGION_ID"><value><![CDATA[47105]]></value></item>
    <item column="REGION_NAME"><value><![CDATA[Loudon]]></value></item>
   </data>
  </region>
  <region>
   <centroid lat="35.6701202392578" lon="-83.9222259521484"/>
   <data>
    <item column="REGION_ID"><value><![CDATA[47009]]></value></item>
    <item column="REGION_NAME"><value><![CDATA[Blount]]></value></item>
   </data>
  </region>
  <region>
   <centroid lat="35.6837596893311" lon="-85.7724952697754"/>
   <data>
    <item column="REGION_ID"><value><![CDATA[47177]]></value></item>
    <item column="REGION_NAME"><value><![CDATA[Warren]]></value></item>
   </data>
  </region>
  <region>
   <centroid lat="35.6205596923828" lon="-88.1042747497559"/>
   <data>
    <item column="REGION_ID"><value><![CDATA[47039]]></value></item>
    <item column="REGION_NAME"><value><![CDATA[Decatur]]></value></item>
   </data>
  </region>
  <region>
   <centroid lat="35.6391143798828" lon="-87.065071105957"/>
   <data>
    <item column="REGION_ID"><value><![CDATA[47119]]></value></item>
    <item column="REGION_NAME"><value><![CDATA[Maury]]></value></item>
   </data>
  </region>
  <region>
   <centroid lat="35.6382827758789" lon="-87.8461990356445"/>
   <data>
    <item column="REGION_ID"><value><![CDATA[47135]]></value></item>
    <item column="REGION_NAME"><value><![CDATA[Perry]]></value></item>
   </data>
  </region>
  <region>
   <centroid lat="35.6229095458984" lon="-84.921558380127"/>
   <data>
    <item column="REGION_ID"><value><![CDATA[47143]]></value></item>
    <item column="REGION_NAME"><value><![CDATA[Rhea]]></value></item>
   </data>
  </region>
  <region>
   <centroid lat="35.6910705566406" lon="-85.4295120239258"/>
   <data>
    <item column="REGION_ID"><value><![CDATA[47175]]></value></item>
    <item column="REGION_NAME"><value><![CDATA[Van Buren]]></value></item>
   </data>
  </region>
  <region>
   <centroid lat="35.6244335174561" lon="-88.3911323547363"/>
   <data>
    <item column="REGION_ID"><value><![CDATA[47077]]></value></item>
    <item column="REGION_NAME"><value><![CDATA[Henderson]]></value></item>
   </data>
  </region>
  <region>
   <centroid lat="35.6098670959473" lon="-89.2890548706055"/>
   <data>
    <item column="REGION_ID"><value><![CDATA[47075]]></value></item>
    <item column="REGION_NAME"><value><![CDATA[Haywood]]></value></item>
   </data>
  </region>
  <region>
   <centroid lat="35.6169471740723" lon="-88.8368301391602"/>
   <data>
    <item column="REGION_ID"><value><![CDATA[47113]]></value></item>
    <item column="REGION_NAME"><value><![CDATA[Madison]]></value></item>
   </data>
  </region>
  <region>
   <centroid lat="35.5693092346191" lon="-85.1635780334473"/>
   <data>
    <item column="REGION_ID"><value><![CDATA[47007]]></value></item>
    <item column="REGION_NAME"><value><![CDATA[Bledsoe]]></value></item>
   </data>
  </region>
  <region>
   <centroid lat="35.5202331542969" lon="-84.8233222961426"/>
   <data>
    <item column="REGION_ID"><value><![CDATA[47121]]></value></item>
    <item column="REGION_NAME"><value><![CDATA[Meigs]]></value></item>
   </data>
  </region>
  <region>
   <centroid lat="35.4924068450928" lon="-86.7731552124023"/>
   <data>
    <item column="REGION_ID"><value><![CDATA[47117]]></value></item>
    <item column="REGION_NAME"><value><![CDATA[Marshall]]></value></item>
   </data>
  </region>
  <region>
   <centroid lat="35.5043487548828" lon="-86.074405670166"/>
   <data>
    <item column="REGION_ID"><value><![CDATA[47031]]></value></item>
    <item column="REGION_NAME"><value><![CDATA[Coffee]]></value></item>
   </data>
  </region>
  <region>
   <centroid lat="35.5191993713379" lon="-86.4490852355957"/>
   <data>
    <item column="REGION_ID"><value><![CDATA[47003]]></value></item>
    <item column="REGION_NAME"><value><![CDATA[Bedford]]></value></item>
   </data>
  </region>
  <region>
   <centroid lat="35.441349029541" lon="-84.234691619873"/>
   <data>
    <item column="REGION_ID"><value><![CDATA[47123]]></value></item>
    <item column="REGION_NAME"><value><![CDATA[Monroe]]></value></item>
   </data>
  </region>
  <region>
   <centroid lat="35.5338878631592" lon="-87.4936294555664"/>
   <data>
    <item column="REGION_ID"><value><![CDATA[47101]]></value></item>
    <item column="REGION_NAME"><value><![CDATA[Lewis]]></value></item>
   </data>
  </region>
  <region>
   <centroid lat="35.4498805999756" lon="-84.6261444091797"/>
   <data>
    <item column="REGION_ID"><value><![CDATA[47107]]></value></item>
    <item column="REGION_NAME"><value><![CDATA[McMinn]]></value></item>
   </data>
  </region>
  <region>
   <centroid lat="35.5137252807617" lon="-89.7561531066895"/>
   <data>
    <item column="REGION_ID"><value><![CDATA[47167]]></value></item>
    <item column="REGION_NAME"><value><![CDATA[Tipton]]></value></item>
   </data>
  </region>
  <region>
   <centroid lat="35.4232273101807" lon="-88.607666015625"/>
   <data>
    <item column="REGION_ID"><value><![CDATA[47023]]></value></item>
    <item column="REGION_NAME"><value><![CDATA[Chester]]></value></item>
   </data>
  </region>
  <region>
   <centroid lat="35.3646202087402" lon="-85.4226875305176"/>
   <data>
    <item column="REGION_ID"><value><![CDATA[47153]]></value></item>
    <item column="REGION_NAME"><value><![CDATA[Sequatchie]]></value></item>
   </data>
  </region>
  <region>
   <centroid lat="35.3836269378662" lon="-85.704891204834"/>
   <data>
    <item column="REGION_ID"><value><![CDATA[47061]]></value></item>
    <item column="REGION_NAME"><value><![CDATA[Grundy]]></value></item>
   </data>
  </region>
  <region>
   <centroid lat="35.2568130493164" lon="-87.7991523742676"/>
   <data>
    <item column="REGION_ID"><value><![CDATA[47181]]></value></item>
    <item column="REGION_NAME"><value><![CDATA[Wayne]]></value></item>
   </data>
  </region>
  <region>
   <centroid lat="35.2386875152588" lon="-89.969123840332"/>
   <data>
    <item column="REGION_ID"><value><![CDATA[47157]]></value></item>
    <item column="REGION_NAME"><value><![CDATA[Shelby]]></value></item>
   </data>
  </region>
  <region>
   <centroid lat="35.2287788391113" lon="-85.2005958557129"/>
   <data>
    <item column="REGION_ID"><value><![CDATA[47065]]></value></item>
    <item column="REGION_NAME"><value><![CDATA[Hamilton]]></value></item>
   </data>
  </region>
  <region>
   <centroid lat="35.2372417449951" lon="-87.4033889770508"/>
   <data>
    <item column="REGION_ID"><value><![CDATA[47099]]></value></item>
    <item column="REGION_NAME"><value><![CDATA[Lawrence]]></value></item>
   </data>
  </region>
  <region>
   <centroid lat="35.2307567596436" lon="-87.0234336853027"/>
   <data>
    <item column="REGION_ID"><value><![CDATA[47055]]></value></item>
    <item column="REGION_NAME"><value><![CDATA[Giles]]></value></item>
   </data>
  </region>
  <region>
   <centroid lat="35.2178974151611" lon="-88.991527557373"/>
   <data>
    <item column="REGION_ID"><value><![CDATA[47069]]></value></item>
    <item column="REGION_NAME"><value><![CDATA[Hardeman]]></value></item>
   </data>
  </region>
  <region>
   <centroid lat="35.2167873382568" lon="-88.1836891174316"/>
   <data>
    <item column="REGION_ID"><value><![CDATA[47071]]></value></item>
    <item column="REGION_NAME"><value><![CDATA[Hardin]]></value></item>
   </data>
  </region>
  <region>
   <centroid lat="35.2750625610352" lon="-86.3810272216797"/>
   <data>
    <item column="REGION_ID"><value><![CDATA[47127]]></value></item>
    <item column="REGION_NAME"><value><![CDATA[Moore]]></value></item>
   </data>
  </region>
  <region>
   <centroid lat="35.2029094696045" lon="-89.416690826416"/>
   <data>
    <item column="REGION_ID"><value><![CDATA[47047]]></value></item>
    <item column="REGION_NAME"><value><![CDATA[Fayette]]></value></item>
   </data>
  </region>
  <region>
   <centroid lat="35.1956558227539" lon="-88.5750389099121"/>
   <data>
    <item column="REGION_ID"><value><![CDATA[47109]]></value></item>
    <item column="REGION_NAME"><value><![CDATA[McNairy]]></value></item>
   </data>
  </region>
  <region>
   <centroid lat="35.1872653961182" lon="-86.5715980529785"/>
   <data>
    <item column="REGION_ID"><value><![CDATA[47103]]></value></item>
    <item column="REGION_NAME"><value><![CDATA[Lincoln]]></value></item>
   </data>
  </region>
  <region>
   <centroid lat="35.1807994842529" lon="-86.094554901123"/>
   <data>
    <item column="REGION_ID"><value><![CDATA[47051]]></value></item>
    <item column="REGION_NAME"><value><![CDATA[Franklin]]></value></item>
   </data>
  </region>
  <region>
   <centroid lat="35.1757068634033" lon="-84.8522186279297"/>
   <data>
    <item column="REGION_ID"><value><![CDATA[47011]]></value></item>
    <item column="REGION_NAME"><value><![CDATA[Bradley]]></value></item>
   </data>
  </region>
  <region>
   <centroid lat="35.1579055786133" lon="-85.6151962280273"/>
   <data>
    <item column="REGION_ID"><value><![CDATA[47115]]></value></item>
    <item column="REGION_NAME"><value><![CDATA[Marion]]></value></item>
   </data>
  </region>
  <region>
   <centroid lat="35.1397686004639" lon="-84.5311164855957"/>
   <data>
    <item column="REGION_ID"><value><![CDATA[47139]]></value></item>
    <item column="REGION_NAME"><value><![CDATA[Polk]]></value></item>
   </data>
  </region>
 </regions>
</map_data>